README.rst
setup.py
django_packageutils.egg-info/PKG-INFO
django_packageutils.egg-info/SOURCES.txt
django_packageutils.egg-info/dependency_links.txt
django_packageutils.egg-info/requires.txt
django_packageutils.egg-info/top_level.txt
packageutils/__init__.py
packageutils/syncdb/__init__.py
packageutils/syncdb/autouser/__init__.py
packageutils/test/__init__.py
packageutils/testcase/__init__.py
packageutils/testcase/app_testcase.py
tests/__init__.py
tests/database.db
tests/manage.py
tests/runtests.py
tests/settings.py
tests/urls.py
tests/blogs/__init__.py
tests/blogs/forms.py
tests/blogs/models.py
tests/blogs/urls.py
tests/blogs/views.py
tests/blogs/fixtures/test.yaml
tests/blogs/templates/404.html
tests/blogs/templates/blog/entry_confirm_delete.html
tests/blogs/templates/blog/entry_detail.html
tests/blogs/templates/blog/entry_form.html
tests/blogs/templates/blog/entry_list.html
tests/blogs/tests/__init__.py
tests/blogs/tests/test_autouser.py
tests/blogs/tests/test_models.py
tests/blogs/tests/test_testapp.py
tests/blogs/tests/test_views.py
tests/blogs/tests/testapp/__init__.py
tests/blogs/tests/testapp/models.py
tests/blogs/tests/testapp/fixtures/test.yaml
tests/static/css/style.css
tests/static/css/style.scss
tests/static/css/image/edit.png
tests/static/css/image/trash.png
tests/templates/404.html
tests/templates/base.html
tests/templates/blogs/entry_confirm_delete.html
tests/templates/blogs/entry_detail.html
tests/templates/blogs/entry_form.html
tests/templates/blogs/entry_list.html
tests/templates/registration/logged_out.html
tests/templates/registration/login.html