Metadata-Version: 1.0
Name: django-packageutils
Version: 0.1.0
Summary: Utility collection of Django package
Home-page: https://github.com/lambdalisue/django-packageutils
Author: Alisue
Author-email: lambdalisue@hashnote.net
License: MIT
Download-URL: https://github.com/lambdalisue/django-packageutils/tarball/master
Keywords: django package utilty
Platform: UNKNOWN
Classifier: Framework :: Django
Classifier: Intended Audience :: Developers
Classifier: License :: OSI Approved :: MIT License
Classifier: Programming Language :: Python
Classifier: Topic :: Internet :: WWW/HTTP
